slickwd.py
slick_webdriver-1.0.66.dist-info/METADATA
slick_webdriver-1.0.66.dist-info/WHEEL
slick_webdriver-1.0.66.dist-info/top_level.txt
slick_webdriver-1.0.66.dist-info/RECORD
