Metadata-Version: 2.1
Name: slick-webdriver
Version: 1.0.66
Summary: A webdriver / selenium wrapper focusing on code completion, good page class design, and logging.
Home-page: http://www.slickqa.com/webdriver/python
Author: SlickQA Developers
Author-email: UNKNOWN
License: UNKNOWN
Keywords: selenium webdriver testing qa web unittest nose
Platform: UNKNOWN
Requires-Dist: selenium (>=3.4.1)
Requires-Dist: PyDispatcher (>=2.0.3)
Requires-Dist: Appium-Python-Client (==0.26)
Requires-Dist: enum34
